nocasedict/__init__.py
nocasedict/_hashable.py
nocasedict/_keyableby.py
nocasedict/_nocasedict.py
nocasedict/_utils.py
nocasedict/_version.py
nocasedict/_version_scm.py
nocasedict/py.typed
nocasedict-2.1.0.dist-info/licenses/AUTHORS.md
nocasedict-2.1.0.dist-info/licenses/LICENSE
nocasedict-2.1.0.dist-info/METADATA
nocasedict-2.1.0.dist-info/WHEEL
nocasedict-2.1.0.dist-info/top_level.txt
nocasedict-2.1.0.dist-info/zip-safe
nocasedict-2.1.0.dist-info/RECORD
