Metadata-Version: 2.4
Name: nocasedict
Version: 2.1.0
Summary: A case-insensitive list for Python
Author-email: Andreas Maier <maiera@de.ibm.com>
Maintainer-email: Andreas Maier <maiera@de.ibm.com>
License: GNU Lesser General Public License v2 or later (LGPLv2+)
Project-URL: Homepage, https://github.com/pywbem/nocasedict
Project-URL: Bug Tracker, https://github.com/pywbem/nocasedict/issues
Project-URL: Documentation, https://nocasedict.readthedocs.io/en/master/
Project-URL: Source Code, https://github.com/pywbem/nocasedict
Project-URL: Changelog, https://nocasedict.readthedocs.io/en/master/changes.html
Keywords: list,case-insensitive
Platform: any
Classifier: Development Status :: 5 - Production/Stable
Classifier: Intended Audience :: Developers
Classifier: License :: OSI Approved :: GNU Lesser General Public License v2 or later (LGPLv2+)
Classifier: Operating System :: OS Independent
Classifier: Programming Language :: Python :: 3
Classifier: Programming Language :: Python :: 3.8
Classifier: Programming Language :: Python :: 3.9
Classifier: Programming Language :: Python :: 3.10
Classifier: Programming Language :: Python :: 3.11
Classifier: Programming Language :: Python :: 3.12
Classifier: Programming Language :: Python :: 3.13
Classifier: Topic :: Software Development :: Libraries :: Python Modules
Requires-Python: >=3.8
License-File: LICENSE
License-File: AUTHORS.md
Requires-Dist: typing-extensions>=4.7.1; python_version >= "3.8" and python_version <= "3.9"
Dynamic: license-file
